Metadata-Version: 2.1
Name: ctu
Version: 0.2
Summary: A python package to perform same transformation to coco-annotation as performed on the image.
Home-page: https://github.com/Cargill-AI/coco-transform-util
Author: Mohit Rajput
Author-email: mohitrajput901@gmail.com
Maintainer: Mohit Rajput
Maintainer-email: mohitrajput901@gmail.com
License: UNKNOWN
Keywords: COCO,Computer Vision,Deep Learning
Platform: UNKNOWN
Classifier: Development Status :: 3 - Alpha
Classifier: Intended Audience :: Science/Research
Classifier: Intended Audience :: Developers
Classifier: Topic :: Software Development :: Libraries
Classifier: Topic :: Scientific/Engineering
Classifier: Topic :: Scientific/Engineering :: Artificial Intelligence
Classifier: Programming Language :: Python
Classifier: Programming Language :: Python :: 3
Classifier: Programming Language :: Python :: 3.4
Classifier: Programming Language :: Python :: 3.5
Classifier: Programming Language :: Python :: 3.6
